gloxon/__init__.py
gloxon/client.py
gloxon-0.1.0.dist-info/LICENSE
gloxon-0.1.0.dist-info/METADATA
gloxon-0.1.0.dist-info/WHEEL
gloxon-0.1.0.dist-info/top_level.txt
gloxon-0.1.0.dist-info/RECORD
